setup.py
upr/__init__.py
upr/connection.py
upr/constants.py
upr/operation.py
upr.egg-info/PKG-INFO
upr.egg-info/SOURCES.txt
upr.egg-info/dependency_links.txt
upr.egg-info/top_level.txt