Metadata-Version: 1.1
Name: upr
Version: 0.2
Summary: Basic UPR client
Home-page: UNKNOWN
Author: Pavel Paulau
Author-email: pavel.paulau@gmail.com
License: UNKNOWN
Platform: UNKNOWN
Classifier: Programming Language :: Python
Classifier: Programming Language :: Python :: 2.7
Classifier: Development Status :: 5 - Production/Stable
Classifier: License :: OSI Approved :: Apache Software License
Classifier: Operating System :: OS Independent
Classifier: Topic :: Software Development :: Libraries :: Python Modules
